molasses_python/__init__.py
MolassesClient-0.1.0.dist-info/AUTHORS.rst
MolassesClient-0.1.0.dist-info/LICENSE
MolassesClient-0.1.0.dist-info/METADATA
MolassesClient-0.1.0.dist-info/WHEEL
MolassesClient-0.1.0.dist-info/top_level.txt
MolassesClient-0.1.0.dist-info/RECORD
