Metadata-Version: 2.1
Name: MolassesClient
Version: 0.1.0
Summary: python SDK for Molasses - feature flags as a service
Home-page: https://github.com/molassesapp/molasses_python
Author: James Hrisho
Author-email: admin@molasses.app
License: MIT license
Keywords: molasses_python
Platform: UNKNOWN
Classifier: Development Status :: 2 - Pre-Alpha
Classifier: Intended Audience :: Developers
Classifier: License :: OSI Approved :: MIT License
Classifier: Natural Language :: English
Classifier: Programming Language :: Python :: 3
Classifier: Programming Language :: Python :: 3.5
Classifier: Programming Language :: Python :: 3.6
Classifier: Programming Language :: Python :: 3.7
Classifier: Programming Language :: Python :: 3.8
Requires-Python: >=3.5
Requires-Dist: requests (==2.24.0)
Requires-Dist: APScheduler (==3.6.3)
